setup.py
fivehundredpx/__init__.py
fivehundredpx/auth.py
fivehundredpx/bind.py
fivehundredpx/client.py
fivehundredpx/errors.py
fivehundredpx/oauth.py
fivehundredpx/settings.py
fivehundredpx/utils.py
python_500px.egg-info/PKG-INFO
python_500px.egg-info/SOURCES.txt
python_500px.egg-info/dependency_links.txt
python_500px.egg-info/requires.txt
python_500px.egg-info/top_level.txt
python_500px.egg-info/zip-safe
tests/__init__.py
tests/base.py
tests/blog.py
tests/collection.py
tests/oauth.py
tests/photo.py
tests/upload.py
tests/user.py