Metadata-Version: 1.0
Name: python-500px
Version: 0.2.0
Summary: 500PX API client
Home-page: https://github.com/akirahrkw/python-500px
Author: Akira Hirakawa
Author-email: akirahrkw@gmail.com
License: MIT
Keywords: 500px
Platform: UNKNOWN
